pyICSParser/RFC5546_SCM.py
pyICSParser/__init__.py
pyICSParser/icalendar_SCM.py
pyICSParser/pyiCalendar.py
pyICSParser-0.7.4.dist-info/METADATA
pyICSParser-0.7.4.dist-info/WHEEL
pyICSParser-0.7.4.dist-info/top_level.txt
pyICSParser-0.7.4.dist-info/RECORD
