Metadata-Version: 2.1
Name: pyICSParser
Version: 0.7.4
Summary: Module supporting the iCalendar specification as defined in RFC5545 as well as its predecessor RFC2445 and non-standard deviances from iCal (Apple), Outlook-calendar (Microsoft), ... 
Home-page: http://ical2list.appspot.com
Author: Oberron
Author-email: one.annum@gmail.com
License: LICENSE.txt
Project-URL: Bug Tracker, https://github.com/1-annum/pyICSParser/issues
Keywords: iCalendar ical ics parser validator generator events enumerator rfc5545 rfc2445 vcal
Classifier: Development Status :: 3 - Alpha
Classifier: Topic :: Utilities
Classifier: License :: OSI Approved :: BSD License
Classifier: Environment :: Console
Classifier: Intended Audience :: End Users/Desktop
Classifier: Intended Audience :: Developers
Classifier: Operating System :: OS Independent
Classifier: Programming Language :: Python :: 2.7
Classifier: Programming Language :: Python :: 3.7
Classifier: Topic :: Utilities
